__init__.py
event.py
image.py
nonebot_plugin_luoguluck-1.0.dist-info/METADATA
nonebot_plugin_luoguluck-1.0.dist-info/WHEEL
nonebot_plugin_luoguluck-1.0.dist-info/entry_points.txt
nonebot_plugin_luoguluck-1.0.dist-info/licenses/LICENSE
nonebot_plugin_luoguluck-1.0.dist-info/RECORD
