Metadata-Version: 2.1
Name: nonebot-plugin-luoguluck
Version: 1.0
Summary: Today's fortune, just like Luogu's!
Keywords: chat,suggar,nonebot
Author-Email: JohnRichard4096 <windowserror@163.com>
License: GPL-3.0-or-later
Project-URL: Homepage, https://github.com/JohnRichard4096/luogu-luck
Project-URL: Source, https://github.com/JohnRichard4096/luogu-luck
Project-URL: Issue Tracker, https://github.com/JohnRichard4096/luogu-luck/issues
Requires-Python: <4.0,>=3.9
Requires-Dist: nonebot2>=2.2.0
Requires-Dist: nonebot-adapter-onebot>=2.0.0
Requires-Dist: pillow>=9.2.0
Requires-Dist: nonebot-plugin-localstore>=0.7
